pyobservable.py
pyobservable-1.0.1.dist-info/LICENSE.txt
pyobservable-1.0.1.dist-info/METADATA
pyobservable-1.0.1.dist-info/WHEEL
pyobservable-1.0.1.dist-info/top_level.txt
pyobservable-1.0.1.dist-info/RECORD
