Metadata-Version: 2.1
Name: pyobservable
Version: 1.0.1
Summary: Simple event system for Python with weak reference support
Home-page: https://github.com/Crimson-Crow/pyobservable
Author: Crimson-Crow
Author-email: github@crimsoncrow.dev
License: MIT
Project-URL: Bug Reports, https://github.com/Crimson-Crow/pyobservable/issues
Project-URL: Source, https://github.com/Crimson-Crow/pyobservable
Keywords: observer observable event handler dispatcher weakref
Platform: UNKNOWN
Classifier: Development Status :: 5 - Production/Stable
Classifier: Intended Audience :: Developers
Classifier: License :: OSI Approved :: MIT License
Classifier: Operating System :: OS Independent
Classifier: Typing :: Typed
Classifier: Programming Language :: Python :: 3
Classifier: Programming Language :: Python :: 3.6
Classifier: Programming Language :: Python :: 3.7
Classifier: Programming Language :: Python :: 3.8
Classifier: Programming Language :: Python :: 3.9
Classifier: Programming Language :: Python :: 3 :: Only
Requires-Python: >=3.6, <4
License-File: LICENSE.txt
Provides-Extra: dev
Requires-Dist: check-manifest ; extra == 'dev'
Provides-Extra: test
Requires-Dist: coverage ; extra == 'test'
